setup.py
easy_eda_visualizations/__init__.py
easy_eda_visualizations/eda.py
easy_eda_visualizations.egg-info/PKG-INFO
easy_eda_visualizations.egg-info/SOURCES.txt
easy_eda_visualizations.egg-info/dependency_links.txt
easy_eda_visualizations.egg-info/not-zip-safe
easy_eda_visualizations.egg-info/top_level.txt