Metadata-Version: 1.0
Name: easy-eda-visualizations
Version: 0.2
Summary: Package to perform EDA activities on a dataframe
Home-page: UNKNOWN
Author: UNKNOWN
Author-email: UNKNOWN
License: UNKNOWN
Platform: UNKNOWN
